{
  "name": "Mithra the Thunder Vassal",
  "number": "22404675",
  "is_illegal": false,
  "text": "If this card is in your hand: You can activate this effect; you cannot Special Summon monsters from the Extra Deck for the rest of this turn, also Special Summon this card, and if you do, Special Summon 1 \"Vassal Token\" (Thunder-Type/LIGHT/Level 1/ATK 800/DEF 1000) to your opponent's field in Defense Position. If this card is Tributed for a Tribute Summon: You can activate this effect; you can Tribute Summon 1 monster during your Main Phase this turn, in addition to your Normal Summon/Set this turn. (You can only gain this effect once per turn.) You can only use each effect of \"Mithra the Thunder Vassal\" once per turn.",
  "type": "Monster",
  "is_monster": true,
  "is_spell": false,
  "is_trap": false,
  "species": "Thunder",
  "attack": "800",
  "defense": "1000",
  "attribute": "LIGHT",
  "is_pendulum": false,
  "is_xyz": false,
  "is_synchro": false,
  "is_fusion": false,
  "is_link": false,
  "is_extra_deck": false,
  "monster_types": [
    "Effect"
  ],
  "stars": "2"
}